Rankchem/Highlighting.py
Rankchem/Ranking.py
Rankchem/__init__.py
RankChem-1.2.5.dist-info/LICENSE
RankChem-1.2.5.dist-info/METADATA
RankChem-1.2.5.dist-info/WHEEL
RankChem-1.2.5.dist-info/top_level.txt
RankChem-1.2.5.dist-info/RECORD
