Metadata-Version: 2.1
Name: RankChem
Version: 1.2.5
Summary: RankChem project
Home-page: https://github.com/fracaludo/RankChem
Author: Emma Kappeler, Ludovica Fracassi
Author-email: Emma Kappeler <emma.kappeler@epfl.ch>, Ludovica Fracassi <ludovica.fracassi@epfl.ch>
License: MIT License
Project-URL: Homepage, https://github.com/fracaludo/RankChem
Classifier: Development Status :: 3 - Alpha
Classifier: Intended Audience :: Developers
Classifier: License :: OSI Approved :: MIT License
Classifier: Operating System :: OS Independent
Classifier: Programming Language :: Python
Classifier: Programming Language :: Python :: 3
Classifier: Programming Language :: Python :: 3.8
Classifier: Programming Language :: Python :: 3.9
Classifier: Programming Language :: Python :: 3.10
Classifier: Programming Language :: Python :: 3.11
Requires-Python: >=3.8
License-File: LICENSE
Requires-Dist: rdkit
Requires-Dist: morfeus-ml
Requires-Dist: pyvistaqt
Requires-Dist: numpy
Requires-Dist: py3Dmol
Requires-Dist: streamlit
Requires-Dist: stmol
Requires-Dist: ipython-genutils
Provides-Extra: test
Requires-Dist: hypothesis ; extra == 'test'
Requires-Dist: pytest ; extra == 'test'
Requires-Dist: pytest-cov ; extra == 'test'
Requires-Dist: tox ; extra == 'test'
Requires-Dist: genbadge[coverage] ; extra == 'test'
